LICENSE
MANIFEST.in
README.rst
setup.cfg
setup.py
test_settings.py
django_simple_forums.egg-info/PKG-INFO
django_simple_forums.egg-info/SOURCES.txt
django_simple_forums.egg-info/dependency_links.txt
django_simple_forums.egg-info/not-zip-safe
django_simple_forums.egg-info/requires.txt
django_simple_forums.egg-info/top_level.txt
docs/Makefile
docs/changelog.rst
docs/conf.py
docs/configuration.rst
docs/index.rst
docs/installation.rst
docs/notifications.rst
docs/overview.rst
docs/searching.rst
docs/templates.rst
simple_forums/__init__.py
simple_forums/admin.py
simple_forums/context_processors.py
simple_forums/forms.py
simple_forums/markup_renderers.py
simple_forums/mixins.py
simple_forums/models.py
simple_forums/urls.py
simple_forums/utils.py
simple_forums/views.py
simple_forums/backends/__init__.py
simple_forums/backends/search/__init__.py
simple_forums/backends/search/base_search.py
simple_forums/backends/search/elastic_search.py
simple_forums/backends/search/simple_search.py
simple_forums/management/__init__.py
simple_forums/management/commands/__init__.py
simple_forums/management/commands/updateindex.py
simple_forums/migrations/0001_initial.py
simple_forums/migrations/0002_message_time_created.py
simple_forums/migrations/0003_message_user.py
simple_forums/migrations/0004_auto_20160201_1656.py
simple_forums/migrations/0005_thread_slug.py
simple_forums/migrations/0006_thread_time_created.py
simple_forums/migrations/0007_topic.py
simple_forums/migrations/0008_thread_topic.py
simple_forums/migrations/0009_topic_slug.py
simple_forums/migrations/0010_thread_sticky.py
simple_forums/migrations/0011_thread_time_last_activity.py
simple_forums/migrations/0012_auto_20160412_1244.py
simple_forums/migrations/__init__.py
simple_forums/notifications/__init__.py
simple_forums/notifications/admin.py
simple_forums/notifications/apps.py
simple_forums/notifications/models.py
simple_forums/notifications/signals.py
simple_forums/notifications/testing_utils.py
simple_forums/notifications/urls.py
simple_forums/notifications/views.py
simple_forums/notifications/migrations/0001_initial.py
simple_forums/notifications/migrations/__init__.py
simple_forums/notifications/templates/simple_forums/notifications/emails/thread_update.html
